odoo10_addon_purchase_date_planned_manual-10.0.1.0.0.99.dev2-py3.8-nspkg.pth
odoo/addons/purchase_date_planned_manual/README.rst
odoo/addons/purchase_date_planned_manual/__init__.py
odoo/addons/purchase_date_planned_manual/__manifest__.py
odoo/addons/purchase_date_planned_manual/i18n/de.po
odoo/addons/purchase_date_planned_manual/i18n/es.po
odoo/addons/purchase_date_planned_manual/i18n/es_MX.po
odoo/addons/purchase_date_planned_manual/i18n/fi.po
odoo/addons/purchase_date_planned_manual/i18n/fr.po
odoo/addons/purchase_date_planned_manual/i18n/fr_FR.po
odoo/addons/purchase_date_planned_manual/i18n/gl.po
odoo/addons/purchase_date_planned_manual/i18n/hr.po
odoo/addons/purchase_date_planned_manual/i18n/it.po
odoo/addons/purchase_date_planned_manual/i18n/nl.po
odoo/addons/purchase_date_planned_manual/i18n/pt_BR.po
odoo/addons/purchase_date_planned_manual/i18n/pt_PT.po
odoo/addons/purchase_date_planned_manual/i18n/purchase_date_planned_manual.pot
odoo/addons/purchase_date_planned_manual/i18n/ro.po
odoo/addons/purchase_date_planned_manual/i18n/sl.po
odoo/addons/purchase_date_planned_manual/i18n/tr_TR.po
odoo/addons/purchase_date_planned_manual/i18n/vi_VN.po
odoo/addons/purchase_date_planned_manual/i18n/zh_CN.po
odoo/addons/purchase_date_planned_manual/models/__init__.py
odoo/addons/purchase_date_planned_manual/models/procurement_order.py
odoo/addons/purchase_date_planned_manual/models/purchase_order.py
odoo/addons/purchase_date_planned_manual/static/description/icon.png
odoo/addons/purchase_date_planned_manual/tests/__init__.py
odoo/addons/purchase_date_planned_manual/tests/test_date_planned_manual.py
odoo/addons/purchase_date_planned_manual/views/purchase_order_view.xml
odoo10_addon_purchase_date_planned_manual-10.0.1.0.0.99.dev2.dist-info/METADATA
odoo10_addon_purchase_date_planned_manual-10.0.1.0.0.99.dev2.dist-info/WHEEL
odoo10_addon_purchase_date_planned_manual-10.0.1.0.0.99.dev2.dist-info/namespace_packages.txt
odoo10_addon_purchase_date_planned_manual-10.0.1.0.0.99.dev2.dist-info/top_level.txt
odoo10_addon_purchase_date_planned_manual-10.0.1.0.0.99.dev2.dist-info/RECORD
